sarm_sdk/__init__.py
sarm_sdk/client.py
sarm_sdk/client_v2.py
sarm_sdk/exceptions.py
sarm_sdk/plugin.py
sarm_sdk/plugin_v2.py
sarm_sdk/py.typed
sarm_sdk/apis/__init__.py
sarm_sdk/apis/application.py
sarm_sdk/apis/application_v2.py
sarm_sdk/apis/business_system.py
sarm_sdk/apis/business_system_v2.py
sarm_sdk/apis/carrier.py
sarm_sdk/apis/carrier_data_import.py
sarm_sdk/apis/carrier_data_import_v2.py
sarm_sdk/apis/carrier_v2.py
sarm_sdk/apis/common.py
sarm_sdk/apis/common_v2.py
sarm_sdk/apis/component.py
sarm_sdk/apis/component_v2.py
sarm_sdk/apis/issue_data_import.py
sarm_sdk/apis/issue_data_import_v2.py
sarm_sdk/apis/organization.py
sarm_sdk/apis/organization_v2.py
sarm_sdk/apis/organize_user.py
sarm_sdk/apis/organize_user_v2.py
sarm_sdk/apis/security_capability.py
sarm_sdk/apis/security_capability_v2.py
sarm_sdk/apis/security_issue.py
sarm_sdk/apis/security_issue_v2.py
sarm_sdk/apis/vulnerability.py
sarm_sdk/apis/vulnerability_v2.py
sarm_sdk/models/__init__.py
sarm_sdk/models/business_system.py
sarm_sdk/models/carrier.py
sarm_sdk/models/carrier_vuln_payload.py
sarm_sdk/models/component.py
sarm_sdk/models/organization.py
sarm_sdk/models/response.py
sarm_sdk/models/security_capability.py
sarm_sdk/models/security_issue.py
sarm_sdk/models/vulnerability.py
sarm_sdk-2.0.2.dist-info/METADATA
sarm_sdk-2.0.2.dist-info/WHEEL
sarm_sdk-2.0.2.dist-info/top_level.txt
sarm_sdk-2.0.2.dist-info/RECORD
