Metadata-Version: 2.4
Name: sarm-sdk
Version: 2.0.2
Summary: Python SDK for SARM(Security Asset Risk Management) Platform
Home-page: https://github.com/murphysec
Author: Murphysec Team
Author-email: Murphysec Team <developer@murphysec.com>
License: MIT
Project-URL: Homepage, https://www.murphysec.com
Keywords: security,asset,risk,management,sdk,api
Classifier: Development Status :: 4 - Beta
Classifier: Intended Audience :: Developers
Classifier: Topic :: Security
Classifier: Topic :: Software Development :: Libraries :: Python Modules
Classifier: License :: OSI Approved :: MIT License
Classifier: Programming Language :: Python :: 3
Classifier: Programming Language :: Python :: 3.7
Classifier: Programming Language :: Python :: 3.8
Classifier: Programming Language :: Python :: 3.9
Classifier: Programming Language :: Python :: 3.10
Classifier: Programming Language :: Python :: 3.11
Classifier: Programming Language :: Python :: 3.12
Requires-Python: >=3.7
Requires-Dist: requests>=2.20.0
Requires-Dist: pydantic>=1.6.0
Requires-Dist: typing-extensions>=3.7.4
Provides-Extra: dev
Requires-Dist: pytest>=6.0; extra == "dev"
Requires-Dist: pytest-cov>=2.0; extra == "dev"
Requires-Dist: black>=21.0; extra == "dev"
Requires-Dist: flake8>=3.8; extra == "dev"
Requires-Dist: mypy>=0.812; extra == "dev"
Requires-Dist: pre-commit>=2.0; extra == "dev"
Provides-Extra: docs
Requires-Dist: sphinx>=4.0; extra == "docs"
Requires-Dist: sphinx-rtd-theme>=0.5; extra == "docs"
Requires-Dist: myst-parser>=0.15; extra == "docs"
Dynamic: author
Dynamic: home-page
Dynamic: requires-python
